odoo/addons/website_event_questions_by_ticket/README.rst
odoo/addons/website_event_questions_by_ticket/__init__.py
odoo/addons/website_event_questions_by_ticket/__manifest__.py
odoo/addons/website_event_questions_by_ticket/i18n/es.po
odoo/addons/website_event_questions_by_ticket/i18n/it.po
odoo/addons/website_event_questions_by_ticket/i18n/website_event_questions_by_ticket.pot
odoo/addons/website_event_questions_by_ticket/models/__init__.py
odoo/addons/website_event_questions_by_ticket/models/event_event.py
odoo/addons/website_event_questions_by_ticket/readme/CONFIGURE.rst
odoo/addons/website_event_questions_by_ticket/readme/CONTRIBUTORS.rst
odoo/addons/website_event_questions_by_ticket/readme/DESCRIPTION.rst
odoo/addons/website_event_questions_by_ticket/readme/ROADMAP.rst
odoo/addons/website_event_questions_by_ticket/readme/USAGE.rst
odoo/addons/website_event_questions_by_ticket/static/description/icon.png
odoo/addons/website_event_questions_by_ticket/static/description/index.html
odoo/addons/website_event_questions_by_ticket/tests/__init__.py
odoo/addons/website_event_questions_by_ticket/tests/test_ticket.py
odoo/addons/website_event_questions_by_ticket/views/event_event_views.xml
odoo/addons/website_event_questions_by_ticket/views/event_templates.xml
odoo14_addon_website_event_questions_by_ticket-14.0.1.0.1.dev8.dist-info/METADATA
odoo14_addon_website_event_questions_by_ticket-14.0.1.0.1.dev8.dist-info/WHEEL
odoo14_addon_website_event_questions_by_ticket-14.0.1.0.1.dev8.dist-info/top_level.txt
odoo14_addon_website_event_questions_by_ticket-14.0.1.0.1.dev8.dist-info/RECORD
